aapt2/__init__.py
aapt2/aapt.py
aapt2/bin/Darwin/aapt2
aapt2/bin/Linux/aapt2
aapt2/bin/Windows/aapt2.exe
aapt2-0.2.1.dist-info/LICENSE
aapt2-0.2.1.dist-info/WHEEL
aapt2-0.2.1.dist-info/METADATA
aapt2-0.2.1.dist-info/RECORD
